metamart_source_dbt_cloud/__init__.py
metamart_source_dbt_cloud/base.py
metamart_source_dbt_cloud/loader.py
metamart_source_dbt_cloud/py.typed
metamart_source_dbt_cloud-0.1.5.dist-info/METADATA
metamart_source_dbt_cloud-0.1.5.dist-info/WHEEL
metamart_source_dbt_cloud-0.1.5.dist-info/RECORD
